jirafs_graphviz/__init__.py
jirafs_graphviz/plugin.py
jirafs_graphviz-3.0.1.dist-info/METADATA
jirafs_graphviz-3.0.1.dist-info/WHEEL
jirafs_graphviz-3.0.1.dist-info/entry_points.txt
jirafs_graphviz-3.0.1.dist-info/top_level.txt
jirafs_graphviz-3.0.1.dist-info/RECORD
