Metadata-Version: 2.1
Name: jirafs-graphviz
Version: 3.0.1
Summary: Automatically convert graphviz DOT files into PNG images when uploading to JIRA
Home-page: https://github.com/coddingtonbear/jirafs-graphviz
Author: Adam Coddington
Author-email: me@adamcoddington.net
License: UNKNOWN
Platform: UNKNOWN
Classifier: License :: OSI Approved :: MIT License
Classifier: Operating System :: OS Independent
Classifier: Programming Language :: Python :: 3
Requires-Dist: six
